py_straight_skeleton/__init__.py
py_straight_skeleton/algorithm.py
py_straight_skeleton/constants.py
py_straight_skeleton/plotting.py
py_straight_skeleton/polygon_math.py
py_straight_skeleton/skeleton.py
py_straight_skeleton/vector_math.py
py_straight_skeleton-0.1.0.dist-info/LICENSE
py_straight_skeleton-0.1.0.dist-info/METADATA
py_straight_skeleton-0.1.0.dist-info/WHEEL
py_straight_skeleton-0.1.0.dist-info/RECORD
