Metadata-Version: 2.1
Name: py_straight_skeleton
Version: 0.1.0
Summary: Compute the straight skeleton of a polygon and its resulting polygonal faces.
License: 3-Clause BSD
Author: Raul Sampedro
Requires-Python: >=3.10,<4.0
Classifier: License :: Other/Proprietary License
Classifier: Programming Language :: Python :: 3
Classifier: Programming Language :: Python :: 3.10
Classifier: Programming Language :: Python :: 3.11
Requires-Dist: matplotlib (>=3.10.0,<4.0.0)
